[1,0,0,[["cc.CompactValueTypeArray",["_unitCount","_unitElement","_length","_byteOffset"],-1],["cc.AnimationClip",["_name","_native","sample","wrapMode","_duration","_hash","_keys","_curves"],-3,9,12],["cc.animation.HierarchyPath",["path"],2]],[[0,3,0,1,2,5],[2,0,2],[1,0,1,2,3,4,5,6,7,7],[0,0,1,2,4]],[[2,"idle",".bin",30,2,2.6666666666666665,2199463042,[[0,58720,65,6,65],[0,58980,65,6,65],[0,59240,65,6,65],[0,59500,63,6,63],[0,59752,65,6,65],[0,60012,65,6,65],[0,60272,65,6,65],[0,60532,65,6,65],[0,60792,35,6,35],[0,60932,65,6,65],[0,61192,65,6,65],[0,61452,65,6,65],[0,61712,65,6,65],[0,61972,65,6,65],[0,62232,65,6,65],[0,62492,65,6,65],[0,62752,65,6,65],[0,63012,65,6,65],[0,63272,65,6,65],[0,63532,65,6,65],[0,63792,65,6,65],[0,64052,65,6,65],[0,64312,65,6,65],[0,64572,2,6,2]],[[[{},"modifiers",12,[[-1,"position"],1,0],"data",11,[{"keys":0},"values",4,[3,195,22,65]]],[{},"modifiers",12,[[-2,"rotation"],1,0],"data",11,[{"keys":0},"values",4,[0,780,260,38,65]]],[{},"modifiers",12,[[-3,"scale"],1,0],"data",11,[{"keys":0},"values",4,[0,1820,195,22,65]]],[{},"modifiers",12,[[-4,"position"],1,0],"data",11,[{"keys":1},"values",4,[0,2600,195,22,65]]],[{},"modifiers",12,[[-5,"rotation"],1,0],"data",11,[{"keys":1},"values",4,[0,3380,260,38,65]]],[{},"modifiers",12,[[-6,"scale"],1,0],"data",11,[{"keys":1},"values",4,[0,4420,195,22,65]]],[{},"modifiers",12,[[-7,"position"],1,0],"data",11,[{"keys":2},"values",4,[0,5200,195,22,65]]],[{},"modifiers",12,[[-8,"rotation"],1,0],"data",11,[{"keys":2},"values",4,[0,5980,260,38,65]]],[{},"modifiers",12,[[-9,"scale"],1,0],"data",11,[{"keys":2},"values",4,[0,7020,195,22,65]]],[{},"modifiers",12,[[-10,"position"],1,0],"data",11,[{"keys":3},"values",4,[0,7800,192,22,64]]],[{},"modifiers",12,[[-11,"rotation"],1,0],"data",11,[{"keys":3},"values",4,[0,8568,256,38,64]]],[{},"modifiers",12,[[-12,"scale"],1,0],"data",11,[{"keys":3},"values",4,[0,9592,192,22,64]]],[{},"modifiers",12,[[-13,"position"],1,0],"data",11,[{"keys":4},"values",4,[0,10360,195,22,65]]],[{},"modifiers",12,[[-14,"rotation"],1,0],"data",11,[{"keys":4},"values",4,[0,11140,260,38,65]]],[{},"modifiers",12,[[-15,"scale"],1,0],"data",11,[{"keys":4},"values",4,[0,12180,195,22,65]]],[{},"modifiers",12,[[-16,"position"],1,0],"data",11,[{"keys":5},"values",4,[0,12960,195,22,65]]],[{},"modifiers",12,[[-17,"rotation"],1,0],"data",11,[{"keys":5},"values",4,[0,13740,260,38,65]]],[{},"modifiers",12,[[-18,"scale"],1,0],"data",11,[{"keys":5},"values",4,[0,14780,195,22,65]]],[{},"modifiers",12,[[-19,"position"],1,0],"data",11,[{"keys":6},"values",4,[0,15560,195,22,65]]],[{},"modifiers",12,[[-20,"rotation"],1,0],"data",11,[{"keys":6},"values",4,[0,16340,260,38,65]]],[{},"modifiers",12,[[-21,"scale"],1,0],"data",11,[{"keys":6},"values",4,[0,17380,195,22,65]]],[{},"modifiers",12,[[-22,"position"],1,0],"data",11,[{"keys":7},"values",4,[0,18160,195,22,65]]],[{},"modifiers",12,[[-23,"rotation"],1,0],"data",11,[{"keys":7},"values",4,[0,18940,260,38,65]]],[{},"modifiers",12,[[-24,"scale"],1,0],"data",11,[{"keys":7},"values",4,[0,19980,195,22,65]]],[{},"modifiers",12,[[-25,"position"],1,0],"data",11,[{"keys":8},"values",4,[0,20760,108,22,36]]],[{},"modifiers",12,[[-26,"rotation"],1,0],"data",11,[{"keys":8},"values",4,[0,21192,144,38,36]]],[{},"modifiers",12,[[-27,"scale"],1,0],"data",11,[{"keys":8},"values",4,[0,21768,108,22,36]]],[{},"modifiers",12,[[-28,"position"],1,0],"data",11,[{"keys":9},"values",4,[0,22200,195,22,65]]],[{},"modifiers",12,[[-29,"rotation"],1,0],"data",11,[{"keys":9},"values",4,[0,22980,260,38,65]]],[{},"modifiers",12,[[-30,"scale"],1,0],"data",11,[{"keys":9},"values",4,[0,24020,195,22,65]]],[{},"modifiers",12,[[-31,"position"],1,0],"data",11,[{"keys":10},"values",4,[0,24800,195,22,65]]],[{},"modifiers",12,[[-32,"rotation"],1,0],"data",11,[{"keys":10},"values",4,[0,25580,260,38,65]]],[{},"modifiers",12,[[-33,"scale"],1,0],"data",11,[{"keys":10},"values",4,[0,26620,195,22,65]]],[{},"modifiers",12,[[-34,"position"],1,0],"data",11,[{"keys":11},"values",4,[0,27400,195,22,65]]],[{},"modifiers",12,[[-35,"rotation"],1,0],"data",11,[{"keys":11},"values",4,[0,28180,260,38,65]]],[{},"modifiers",12,[[-36,"scale"],1,0],"data",11,[{"keys":11},"values",4,[0,29220,195,22,65]]],[{},"modifiers",12,[[-37,"position"],1,0],"data",11,[{"keys":12},"values",4,[0,30000,195,22,65]]],[{},"modifiers",12,[[-38,"rotation"],1,0],"data",11,[{"keys":12},"values",4,[0,30780,260,38,65]]],[{},"modifiers",12,[[-39,"scale"],1,0],"data",11,[{"keys":12},"values",4,[0,31820,195,22,65]]],[{},"modifiers",12,[[-40,"position"],1,0],"data",11,[{"keys":13},"values",4,[0,32600,195,22,65]]],[{},"modifiers",12,[[-41,"rotation"],1,0],"data",11,[{"keys":13},"values",4,[0,33380,260,38,65]]],[{},"modifiers",12,[[-42,"scale"],1,0],"data",11,[{"keys":13},"values",4,[0,34420,195,22,65]]],[{},"modifiers",12,[[-43,"position"],1,0],"data",11,[{"keys":14},"values",4,[0,35200,195,22,65]]],[{},"modifiers",12,[[-44,"rotation"],1,0],"data",11,[{"keys":14},"values",4,[0,35980,260,38,65]]],[{},"modifiers",12,[[-45,"scale"],1,0],"data",11,[{"keys":14},"values",4,[0,37020,195,22,65]]],[{},"modifiers",12,[[-46,"position"],1,0],"data",11,[{"keys":15},"values",4,[0,37800,195,22,65]]],[{},"modifiers",12,[[-47,"rotation"],1,0],"data",11,[{"keys":15},"values",4,[0,38580,260,38,65]]],[{},"modifiers",12,[[-48,"scale"],1,0],"data",11,[{"keys":15},"values",4,[0,39620,195,22,65]]],[{},"modifiers",12,[[-49,"position"],1,0],"data",11,[{"keys":16},"values",4,[0,40400,195,22,65]]],[{},"modifiers",12,[[-50,"rotation"],1,0],"data",11,[{"keys":16},"values",4,[0,41180,260,38,65]]],[{},"modifiers",12,[[-51,"scale"],1,0],"data",11,[{"keys":16},"values",4,[0,42220,195,22,65]]],[{},"modifiers",12,[[-52,"position"],1,0],"data",11,[{"keys":17},"values",4,[0,43000,195,22,65]]],[{},"modifiers",12,[[-53,"rotation"],1,0],"data",11,[{"keys":17},"values",4,[0,43780,260,38,65]]],[{},"modifiers",12,[[-54,"scale"],1,0],"data",11,[{"keys":17},"values",4,[0,44820,195,22,65]]],[{},"modifiers",12,[[-55,"position"],1,0],"data",11,[{"keys":18},"values",4,[0,45600,195,22,65]]],[{},"modifiers",12,[[-56,"rotation"],1,0],"data",11,[{"keys":18},"values",4,[0,46380,260,38,65]]],[{},"modifiers",12,[[-57,"scale"],1,0],"data",11,[{"keys":18},"values",4,[0,47420,195,22,65]]],[{},"modifiers",12,[[-58,"position"],1,0],"data",11,[{"keys":19},"values",4,[0,48200,195,22,65]]],[{},"modifiers",12,[[-59,"rotation"],1,0],"data",11,[{"keys":19},"values",4,[0,48980,260,38,65]]],[{},"modifiers",12,[[-60,"scale"],1,0],"data",11,[{"keys":19},"values",4,[0,50020,195,22,65]]],[{},"modifiers",12,[[-61,"position"],1,0],"data",11,[{"keys":20},"values",4,[0,50800,195,22,65]]],[{},"modifiers",12,[[-62,"rotation"],1,0],"data",11,[{"keys":20},"values",4,[0,51580,260,38,65]]],[{},"modifiers",12,[[-63,"scale"],1,0],"data",11,[{"keys":20},"values",4,[0,52620,195,22,65]]],[{},"modifiers",12,[[-64,"position"],1,0],"data",11,[{"keys":21},"values",4,[0,53400,195,22,65]]],[{},"modifiers",12,[[-65,"rotation"],1,0],"data",11,[{"keys":21},"values",4,[0,54180,260,38,65]]],[{},"modifiers",12,[[-66,"scale"],1,0],"data",11,[{"keys":21},"values",4,[0,55220,195,22,65]]],[{},"modifiers",12,[[-67,"position"],1,0],"data",11,[{"keys":22},"values",4,[0,56000,195,22,65]]],[{},"modifiers",12,[[-68,"rotation"],1,0],"data",11,[{"keys":22},"values",4,[0,56780,260,38,65]]],[{},"modifiers",12,[[-69,"scale"],1,0],"data",11,[{"keys":22},"values",4,[0,57820,195,22,65]]],[{},"modifiers",12,[[-70,"position"],1,0],"data",11,[{"keys":23},"values",4,[0,58600,6,22,2]]],[{},"modifiers",12,[[-71,"rotation"],1,0],"data",11,[{"keys":23},"values",4,[0,58624,8,38,2]]],[{},"modifiers",12,[[-72,"scale"],1,0],"data",11,[{"keys":23},"values",4,[0,58656,6,22,2]]],[{},"modifiers",12,[[-73,"position"],1,0],"data",11,[{"keys":-1,"interpolate":false},"values",4,[0,58680,3,22,1]]],[{},"modifiers",12,[[-74,"scale"],1,0],"data",11,[{"keys":-1,"interpolate":false},"values",4,[0,58692,3,22,1]]],[{},"modifiers",12,[[-75,"rotation"],1,0],"data",11,[{"keys":-1,"interpolate":false},"values",4,[0,58704,4,38,1]]]],11,11,11,11,11,11,11,11,11,11,11,11,11,11,11,11,11,11,11,11,11,11,11,11,11,11,11,11,11,11,11,11,11,11,11,11,11,11,11,11,11,11,11,11,11,11,11,11,11,11,11,11,11,11,11,11,11,11,11,11,11,11,11,11,11,11,11,11,11,11,11,11,11,11,11]],[1,"Bip01"],[1,"Bip01/l4"],[1,"Bip01/l4/l5"],[1,"Bip01/l4/l5/l6"],[1,"Bip01/weiba1"],[1,"Bip01/weiba1/weiba2"],[1,"Bip01/r4"],[1,"Bip01/r4/r5"],[1,"Bip01/r4/r5/r6"],[1,"Bip01/r1"],[1,"Bip01/r1/r2"],[1,"Bip01/r1/r2/r3"],[1,"Bip01/l1"],[1,"Bip01/l1/l2"],[1,"Bip01/l1/l2/l3"],[1,"Bip01/bozi"],[1,"Bip01/bozi/tou"],[1,"Bip01/bozi/tou/meimao_l"],[1,"Bip01/bozi/tou/meimao_r"],[1,"Bip01/bozi/tou/yanpi_r"],[1,"Bip01/bozi/tou/eye_r"],[1,"Bip01/bozi/tou/eye_l"],[1,"Bip01/bozi/tou/yanpi_l"],[1,"Bip01/boody"],[1,"body"]],0,[0,-1,1,0,-1,1,0,-1,1,0,-1,2,0,-1,2,0,-1,2,0,-1,3,0,-1,3,0,-1,3,0,-1,4,0,-1,4,0,-1,4,0,-1,5,0,-1,5,0,-1,5,0,-1,6,0,-1,6,0,-1,6,0,-1,7,0,-1,7,0,-1,7,0,-1,8,0,-1,8,0,-1,8,0,-1,9,0,-1,9,0,-1,9,0,-1,10,0,-1,10,0,-1,10,0,-1,11,0,-1,11,0,-1,11,0,-1,12,0,-1,12,0,-1,12,0,-1,13,0,-1,13,0,-1,13,0,-1,14,0,-1,14,0,-1,14,0,-1,15,0,-1,15,0,-1,15,0,-1,16,0,-1,16,0,-1,16,0,-1,17,0,-1,17,0,-1,17,0,-1,18,0,-1,18,0,-1,18,0,-1,19,0,-1,19,0,-1,19,0,-1,20,0,-1,20,0,-1,20,0,-1,21,0,-1,21,0,-1,21,0,-1,22,0,-1,22,0,-1,22,0,-1,23,0,-1,23,0,-1,23,0,-1,24,0,-1,24,0,-1,24,0,-1,25,0,-1,25,0,-1,25,75],[],[],[]]
