[
    1,
    [
        "daItr3UjtEqbeaxWz7/p34@6c48a"
    ],
    [
        "_textureSource"
    ],
    [
        "cc.SpriteFrame"
    ],
    0,
    [
        {
            "name": "list_bg_blue",
            "rect": {
                "x": 0,
                "y": 0,
                "width": 251,
                "height": 97
            },
            "offset": {
                "x": 0,
                "y": 0
            },
            "originalSize": {
                "width": 251,
                "height": 97
            },
            "rotated": false,
            "capInsets": [
                0,
                0,
                0,
                0
            ],
            "texture": "da22daf7-523b-44a9-b79a-c56cfbfe9df8@6c48a"
        }
    ],
    [
        0
    ],
    0,
    [
        0
    ],
    [
        0
    ],
    [
        0
    ]
]
